_exemplo_uso/__init__.py
_exemplo_uso/exemplo_uso.py
pix_qrcode/__init__.py
pix_qrcode/generate_pix_qrcode.py
pix_qrcode/generator.py
pix_qrcode/gui.py
pix_qrcode/utils.py
tests/__init__.py
tests/test_generator.py
pixqrcode_generator-0.1.dist-info/METADATA
pixqrcode_generator-0.1.dist-info/WHEEL
pixqrcode_generator-0.1.dist-info/top_level.txt
pixqrcode_generator-0.1.dist-info/RECORD
