Metadata-Version: 2.1
Name: pixqrcode-generator
Version: 0.1
Summary: Biblioteca para gerar QR Codes de pagamentos via PIX
Home-page: https://github.com/username/pixqrcode-generator
Author: Seu Nome
Author-email: seuemail@exemplo.com
Classifier: Programming Language :: Python :: 3
Classifier: License :: OSI Approved :: MIT License
Classifier: Operating System :: OS Independent
Requires-Python: >=3.6
Requires-Dist: qrcode[pil]
Requires-Dist: Pillow
